eitprocessing/__init__.py
eitprocessing/categories.py
eitprocessing/py.typed
eitprocessing/config/__init__.py
eitprocessing/config/categories-compact.yaml
eitprocessing/datahandling/__init__.py
eitprocessing/datahandling/breath.py
eitprocessing/datahandling/continuousdata.py
eitprocessing/datahandling/datacollection.py
eitprocessing/datahandling/eitdata.py
eitprocessing/datahandling/event.py
eitprocessing/datahandling/intervaldata.py
eitprocessing/datahandling/pixelmap.py
eitprocessing/datahandling/sequence.py
eitprocessing/datahandling/sparsedata.py
eitprocessing/datahandling/loading/__init__.py
eitprocessing/datahandling/loading/binreader.py
eitprocessing/datahandling/loading/draeger.py
eitprocessing/datahandling/loading/sentec.py
eitprocessing/datahandling/loading/timpel.py
eitprocessing/datahandling/mixins/__init__.py
eitprocessing/datahandling/mixins/equality.py
eitprocessing/datahandling/mixins/plotting.py
eitprocessing/datahandling/mixins/slicing.py
eitprocessing/features/__init__.py
eitprocessing/features/breath_detection.py
eitprocessing/features/moving_average.py
eitprocessing/features/pixel_breath.py
eitprocessing/features/rate_detection.py
eitprocessing/filters/__init__.py
eitprocessing/filters/butterworth_filters.py
eitprocessing/filters/mdn.py
eitprocessing/parameters/__init__.py
eitprocessing/parameters/eeli.py
eitprocessing/parameters/tidal_impedance_variation.py
eitprocessing/plotting/__init__.py
eitprocessing/plotting/filter.py
eitprocessing/plotting/helpers.py
eitprocessing/plotting/pixelmap.py
eitprocessing/plotting/rate_detection.py
eitprocessing/roi/__init__.py
eitprocessing/roi/amplitude.py
eitprocessing/roi/filter_by_size.py
eitprocessing/roi/pixelmaskcollection.py
eitprocessing/roi/tiv.py
eitprocessing/roi/watershed.py
eitprocessing/utils/__init__.py
eitprocessing-1.8.7.dist-info/licenses/LICENSE
eitprocessing-1.8.7.dist-info/licenses/NOTICE
eitprocessing-1.8.7.dist-info/METADATA
eitprocessing-1.8.7.dist-info/WHEEL
eitprocessing-1.8.7.dist-info/top_level.txt
eitprocessing-1.8.7.dist-info/RECORD
