Metadata-Version: 2.4
Name: eitprocessing
Version: 1.8.7
Summary: Processing of lung image data from electrical impedance tomography.
Author-email: Dani Bodor <d.bodor@esciencecenter.nl>, Peter Somhorst <p.somhorst@erasmusmc.nl>, Annemijn Jonkman <a.jonkman@erasmusmc.nl>, Walter Baccinelli <w.baccinelli@esciencecenter.nl>, Jantine Wisse-Smit <j.j.smit@erasmusmc.nl>, Juliette Francovich <j.francovich@erasmusmc.nl>
License: Apache-2.0 license
Project-URL: Documentation, https://github.com/EIT-ALIVE/eitprocessing/blob/main/README.md
Project-URL: Repository, https://github.com/EIT-ALIVE/eitprocessing/
Project-URL: Changelog, https://github.com/EIT-ALIVE/eitprocessing/blob/main/CHANGELOG.md
Keywords: Mechanical lung ventilation,Electrical impedance tomography,Image/data processing,Advanced respiratory care
Classifier: Development Status :: 5 - Production/Stable
Classifier: Intended Audience :: Healthcare Industry
Classifier: Intended Audience :: Science/Research
Classifier: Intended Audience :: Developers
Classifier: License :: OSI Approved :: Apache Software License
Classifier: Natural Language :: English
Classifier: Programming Language :: Python :: 3
Classifier: Programming Language :: Python :: 3.10
Classifier: Programming Language :: Python :: 3.11
Classifier: Programming Language :: Python :: 3.12
Classifier: Programming Language :: Python :: 3.13
Requires-Python: >=3.10
License-File: LICENSE
License-File: NOTICE
Requires-Dist: matplotlib>=3.10
Requires-Dist: numpy>=1.24.2
Requires-Dist: scipy>=1.10.1
Requires-Dist: anytree>=2.12.1
Requires-Dist: typing_extensions
Requires-Dist: pyyaml
Requires-Dist: frozendict>=2.4.6
Requires-Dist: scikit-image>=0.25.2
Provides-Extra: dev
Requires-Dist: pytest<8.4.0,>=7.4.0; extra == "dev"
Requires-Dist: bump-my-version==0.28.1; extra == "dev"
Requires-Dist: coverage; extra == "dev"
Requires-Dist: pytest-cov; extra == "dev"
Requires-Dist: coveralls; extra == "dev"
Requires-Dist: ruff==0.12.10; extra == "dev"
Provides-Extra: testing
Requires-Dist: pytest<8.4.0,>=7.4.0; extra == "testing"
Requires-Dist: pytest-cov; extra == "testing"
Requires-Dist: coveralls; extra == "testing"
Provides-Extra: docs
Requires-Dist: mkdocs>=1.6.1; extra == "docs"
Requires-Dist: mkdocs-material>=9.6.18; extra == "docs"
Requires-Dist: mkdocstrings>=0.30.0; extra == "docs"
Requires-Dist: mkdocstrings-python<2.0,>=1.17.0; extra == "docs"
Requires-Dist: mkdocs-exclude>=1.0.2; extra == "docs"
Requires-Dist: mike>=2.1.3; extra == "docs"
Requires-Dist: pymdown-extensions>=10.16.1; extra == "docs"
Requires-Dist: black>=25.1.0; extra == "docs"
Requires-Dist: mkdocs-jupyter>=0.25.1; extra == "docs"
Provides-Extra: notebooks
Requires-Dist: jupyter>=1.0.0; extra == "notebooks"
Requires-Dist: jupytext>=1.14.5; extra == "notebooks"
Requires-Dist: tqdm>=4.65.0; extra == "notebooks"
Requires-Dist: ipympl; extra == "notebooks"
Provides-Extra: publishing
Requires-Dist: build; extra == "publishing"
Dynamic: license-file
